pyzoho_fulfillment/__init__.py
pyzoho_fulfillment/pyzoho.py
pyzoho_fulfillment/response.py
pyzoho_fulfillment-0.0.3.dist-info/LICENSE
pyzoho_fulfillment-0.0.3.dist-info/METADATA
pyzoho_fulfillment-0.0.3.dist-info/WHEEL
pyzoho_fulfillment-0.0.3.dist-info/top_level.txt
pyzoho_fulfillment-0.0.3.dist-info/RECORD
